{
  "project_info": {
    "project_number": "793861462838",
    "firebase_url": "https://songhistory-abba9.firebaseio.com",
    "project_id": "songhistory-abba9",
    "storage_bucket": "songhistory-abba9.appspot.com"
  },
  "client": [
    {
      "client_info": {
        "mobilesdk_app_id": "1:793861462838:android:1780a057f9d17c2c",
        "android_client_info": {
          "package_name": "com.test.kani.songhistory"
        }
      },
      "oauth_client": [
        {
          "client_id": "793861462838-l9r1kusk1kft8gq739drbq47e4gssmed.apps.googleusercontent.com",
          "client_type": 3
        }
      ],
      "api_key": [
        {
          "current_key": "AIzaSyD0WiUpc9yhUY0dwu1acSaR4VG2Xh0CD70"
        }
      ],
      "services": {
        "analytics_service": {
          "status": 1
        },
        "appinvite_service": {
          "status": 1,
          "other_platform_oauth_client": []
        },
        "ads_service": {
          "status": 2
        }
      }
    }
  ],
  "configuration_version": "1"
}